{
  "ai_inference_used": false,
  "canvas_size": {
    "height": 1024,
    "width": 1024
  },
  "chain_events": [],
  "decoded_pixel_hash": "sha256:644774d548e8b5010534602d90fc615929f59aee67e354e47d5f6b3bf111feff",
  "external_assets_used": false,
  "font_family_id": "arial",
  "html_path": "html/sample_000203.html",
  "html_sha256": "sha256:c63b8eb7d81e6fa737b9b1282f0f5defc7b9e540f46bff563bf79b2fe2bda5ef",
  "initial_digital_event": "digital_to_digital_file_export",
  "last_acquisition_event": "none",
  "layout_counts": {
    "cards": 3,
    "charts": 2,
    "sections": 3,
    "tables": 0
  },
  "layout_id": "dashboard_with_charts__government_form__1024x1024__s3_c3_t0_ch1",
  "non_ai_generation": true,
  "output_asset_hash": "sha256:25fec91c820a2606b03a45ae567cc7668d527b93497d1940857d622ecb5bca66",
  "output_format": "png",
  "output_path": "images/sample_000203.png",
  "parent_sample_id": null,
  "random_seed": 20260817,
  "renderer": "playwright_chromium",
  "renderer_version": "playwright 1.60.0; chromium 148.0.7778.96",
  "sample_id": "sample_000203",
  "style_id": "government_form",
  "template_family": "dashboard_with_charts",
  "wordlist_version": "local_wordlists_v1"
}
