{
  "ai_inference_used": false,
  "canvas_size": {
    "height": 1350,
    "width": 1080
  },
  "chain_events": [],
  "decoded_pixel_hash": "sha256:5002c0e71fa612becfc9e08d64f990948ab1a7d812f51bc1a08a57ca053caad2",
  "external_assets_used": false,
  "html_path": "html/sample_000458.html",
  "html_sha256": "sha256:498d5fa802df121edd77e1943ab880f212c619202e3518ad11ca6170218879f6",
  "initial_digital_event": "digital_to_digital_file_export",
  "last_acquisition_event": "none",
  "non_ai_generation": true,
  "output_asset_hash": "sha256:717b7953ed440201bee80484693a5848e7defaeabafb7e6d6e2068d1a574032e",
  "output_format": "png",
  "output_path": "images/sample_000458.png",
  "random_seed": 20261072,
  "renderer": "playwright_chromium",
  "renderer_version": "playwright 1.60.0; chromium 148.0.7778.96",
  "sample_id": "sample_000458",
  "template_id": "dashboard_with_charts",
  "wordlist_version": "local_wordlists_v1"
}
