{
  "ai_inference_used": false,
  "canvas_size": {
    "height": 1350,
    "width": 1080
  },
  "chain_events": [],
  "decoded_pixel_hash": "sha256:35b953d2592eb102b689baa8e45a2b0f3758910850c6f196d2cd9bcff2bb81fd",
  "external_assets_used": false,
  "html_path": "html/sample_000272.html",
  "html_sha256": "sha256:05fbaf5c2728ee85062e60cd0982f6466b6fc1c6db1fef19992f5397489483ff",
  "initial_digital_event": "digital_to_digital_file_export",
  "last_acquisition_event": "none",
  "non_ai_generation": true,
  "output_asset_hash": "sha256:bec80b5785e06f3ecc893024f2426b44511e6d6b8eda35b0717905e58a08bd37",
  "output_format": "png",
  "output_path": "images/sample_000272.png",
  "random_seed": 20260886,
  "renderer": "playwright_chromium",
  "renderer_version": "playwright 1.60.0; chromium 148.0.7778.96",
  "sample_id": "sample_000272",
  "template_id": "report_page",
  "wordlist_version": "local_wordlists_v1"
}
