{
  "ai_inference_used": false,
  "canvas_size": {
    "height": 1350,
    "width": 1080
  },
  "chain_events": [],
  "decoded_pixel_hash": "sha256:4dbfc16afa46fb3bad5ddd32bdbfe0cdaa7bf610bb52b6111f3a902097fdb5c4",
  "external_assets_used": false,
  "html_path": "html/sample_000190.html",
  "html_sha256": "sha256:bdf00835d9b71a730acc6a8b9eb219dc51209e523cad3601cbb4ba258d1e9d14",
  "initial_digital_event": "digital_to_digital_file_export",
  "last_acquisition_event": "none",
  "non_ai_generation": true,
  "output_asset_hash": "sha256:36e0d4fd663047a685ef2376112721a9b97b67fe011b27d89a34398d0afff675",
  "output_format": "png",
  "output_path": "images/sample_000190.png",
  "random_seed": 20260804,
  "renderer": "playwright_chromium",
  "renderer_version": "playwright 1.60.0; chromium 148.0.7778.96",
  "sample_id": "sample_000190",
  "template_id": "poster_info_card",
  "wordlist_version": "local_wordlists_v1"
}
