{
  "ai_inference_used": false,
  "canvas_size": {
    "height": 1280,
    "width": 720
  },
  "chain_events": [
    {
      "event_kind": "manipulation_or_processing",
      "event_type": "digital_recompression",
      "mask_path": null,
      "operation_registry_ref": "pillow_jpeg_recompression",
      "order": 1,
      "parameters": {
        "codec": "jpeg",
        "optimize": false,
        "progressive": false,
        "quality": 90,
        "software": "Pillow",
        "software_version": "11.3.0",
        "source_output_format": "png",
        "subsampling": "4:2:0"
      },
      "scope": "global",
      "semantic_change_degree": "none"
    }
  ],
  "decoded_pixel_hash": "sha256:bc61315655538b4a7c4791b6133edfe740ee3b3d20f7f3668faa09c023ed5133",
  "external_assets_used": false,
  "font_family_id": "times",
  "html_path": "html/sample_000454.html",
  "html_sha256": "sha256:d4a705f17244ded82aea9ac73f7b92a00dc59d2b58cacb66bf197e78c945d533",
  "initial_digital_event": "digital_to_digital_file_export",
  "jpeg_recompression": {
    "optimize": false,
    "progressive": false,
    "quality": 90,
    "software": "Pillow",
    "software_version": "11.3.0",
    "subsampling": "4:2:0"
  },
  "label_status": "controlled_complete",
  "last_acquisition_event": "none",
  "layout_counts": {
    "cards": 2,
    "charts": 1,
    "sections": 4,
    "tables": 2
  },
  "layout_id": "table_form_menu__corporate_blue_gray__720x1280__s4_c2_t2_ch1",
  "non_ai_generation": true,
  "output_asset_hash": "sha256:c53ac9a56205d75fe005a9f5a06fdc51fdbbf8db4b9983e5bc440ac5461125e5",
  "output_format": "jpeg",
  "output_path": "images/sample_000454_jpeg_q90_420.jpg",
  "parent_asset_hashes": [
    "sha256:d17b653675c4078a8e5a4be0ab06ab50f5bbdbb11aa18071ff821e1da15553c5"
  ],
  "parent_sample_id": "sample_000454",
  "random_seed": 20261068,
  "renderer": "playwright_chromium",
  "renderer_version": "playwright 1.60.0; chromium 148.0.7778.96",
  "sample_id": "sample_000454_jpeg_q90_420",
  "source_manifest_path": "/Users/xingzhengpeng/CODEZONE/AIGC Detection/Provenance chain/pilot_export_workflow/generated_pilot_v2_1000/manifests/samples.jsonl",
  "source_output_path": "images/sample_000454.png",
  "style_id": "corporate_blue_gray",
  "template_family": "table_form_menu",
  "wordlist_version": "local_wordlists_v1"
}
