{
  "ai_inference_used": false,
  "canvas_size": {
    "height": 1280,
    "width": 720
  },
  "chain_events": [
    {
      "event_kind": "manipulation_or_processing",
      "event_type": "digital_recompression",
      "mask_path": null,
      "operation_registry_ref": "pillow_jpeg_recompression",
      "order": 1,
      "parameters": {
        "codec": "jpeg",
        "optimize": false,
        "progressive": false,
        "quality": 90,
        "software": "Pillow",
        "software_version": "11.3.0",
        "source_output_format": "png",
        "subsampling": "4:2:0"
      },
      "scope": "global",
      "semantic_change_degree": "none"
    }
  ],
  "decoded_pixel_hash": "sha256:59ee8589cc84841b8b79323a169d067df08f63509ffcf0b114b80578b94279f2",
  "external_assets_used": false,
  "font_family_id": "courier",
  "html_path": null,
  "initial_digital_event": "digital_to_digital_file_export",
  "jpeg_recompression": {
    "optimize": false,
    "progressive": false,
    "quality": 90,
    "software": "Pillow",
    "software_version": "11.3.0",
    "subsampling": "4:2:0"
  },
  "label_status": "controlled_complete",
  "last_acquisition_event": "none",
  "layout_counts": {
    "bars": 5,
    "cards": 3,
    "nodes": 7,
    "paths": 2
  },
  "layout_id": "svg_infographic_card__bold_poster__720x1280__n7_c3_b5_p2",
  "output_asset_hash": "sha256:eaef51b18cd73a4f2fdfb294a961ec9d40072c49ebad6244846637886abcc21a",
  "output_format": "jpeg",
  "output_path": "images/sample_000137_jpeg_q90_420.jpg",
  "parent_asset_hashes": [
    "sha256:dd48424781d448af4490d892a0af7d4e3c3934b6b2365b3c45e4c3e5d76375bf"
  ],
  "parent_sample_id": "sample_000137",
  "random_seed": 20260751,
  "renderer": "playwright_chromium_svg_rasterizer",
  "renderer_version": "playwright 1.60.0; chromium 148.0.7778.96",
  "sample_id": "sample_000137_jpeg_q90_420",
  "schema_version": "provenance_chain_v1",
  "source_asset_hash": "sha256:99bb20d2d21a5987bae37a26791164b55e5f8f9834c26e625ca5f7b7420f13ab",
  "source_manifest_path": "/Users/xingzhengpeng/CODEZONE/AIGC Detection/Provenance chain/pilot_export_workflow/generated_svg_v1_1000/manifests/samples.jsonl",
  "source_output_path": "images/sample_000137.png",
  "source_path": "svg/sample_000137.svg",
  "source_type": "svg",
  "style_id": "bold_poster",
  "template_family": "svg_infographic_card",
  "wordlist_version": "local_wordlists_v1"
}
