{
  "ai_inference_used": false,
  "canvas_size": {
    "height": 1280,
    "width": 720
  },
  "chain_events": [
    {
      "event_kind": "manipulation_or_processing",
      "event_type": "digital_recompression",
      "mask_path": null,
      "operation_registry_ref": "pillow_jpeg_recompression",
      "order": 1,
      "parameters": {
        "codec": "jpeg",
        "optimize": false,
        "progressive": false,
        "quality": 90,
        "software": "Pillow",
        "software_version": "11.3.0",
        "source_output_format": "png",
        "subsampling": "4:2:0"
      },
      "scope": "global",
      "semantic_change_degree": "none"
    }
  ],
  "decoded_pixel_hash": "sha256:4d35c1154908c6f1e4ebd3fca1d52072159330ac2019d734e0e3eb465c21bbff",
  "external_assets_used": false,
  "font_family_id": "times",
  "html_path": null,
  "initial_digital_event": "digital_to_digital_file_export",
  "jpeg_recompression": {
    "optimize": false,
    "progressive": false,
    "quality": 90,
    "software": "Pillow",
    "software_version": "11.3.0",
    "subsampling": "4:2:0"
  },
  "label_status": "controlled_complete",
  "last_acquisition_event": "none",
  "layout_counts": {
    "bars": 5,
    "cards": 6,
    "nodes": 7,
    "paths": 3
  },
  "layout_id": "svg_data_badge_sheet__government_form__720x1280__n7_c6_b5_p3",
  "output_asset_hash": "sha256:71c3b324852c35ff928df9d75069397110a59355022bdcd3a268db5bad4b355d",
  "output_format": "jpeg",
  "output_path": "images/sample_000519_jpeg_q90_420.jpg",
  "parent_asset_hashes": [
    "sha256:e607e39742921bec63908bf50ccc55ba21e016a4253d24d4237233cd03fce7c5"
  ],
  "parent_sample_id": "sample_000519",
  "random_seed": 20261133,
  "renderer": "playwright_chromium_svg_rasterizer",
  "renderer_version": "playwright 1.60.0; chromium 148.0.7778.96",
  "sample_id": "sample_000519_jpeg_q90_420",
  "schema_version": "provenance_chain_v1",
  "source_asset_hash": "sha256:32b8531f75d15ea9aeb9ba417123d4338ced22336cd9528f6b62957f5119ff7f",
  "source_manifest_path": "/Users/xingzhengpeng/CODEZONE/AIGC Detection/Provenance chain/pilot_export_workflow/generated_svg_v1_1000/manifests/samples.jsonl",
  "source_output_path": "images/sample_000519.png",
  "source_path": "svg/sample_000519.svg",
  "source_type": "svg",
  "style_id": "government_form",
  "template_family": "svg_data_badge_sheet",
  "wordlist_version": "local_wordlists_v1"
}
