{
  "ai_inference_used": false,
  "canvas_size": {
    "height": 1024,
    "width": 1024
  },
  "chain_events": [],
  "decoded_pixel_hash": "sha256:8e6d21264424b99742823fc1261438704f1ecffd7f33dad82c7eb1833dc874c4",
  "external_assets_used": false,
  "font_family_id": "courier",
  "initial_digital_event": "digital_to_digital_file_export",
  "label_status": "controlled_complete",
  "last_acquisition_event": "none",
  "layout_counts": {
    "bars": 8,
    "cards": 5,
    "nodes": 8,
    "paths": 2
  },
  "layout_id": "svg_flowchart_diagram__minimal_white__1024x1024__n8_c5_b8_p2",
  "output_asset_hash": "sha256:1cd1433d92800be9098adca6570a9d44333f55a9f277eac555dc9ee7f550cb6b",
  "output_format": "png",
  "output_path": "images/sample_000130.png",
  "parent_asset_hashes": [
    "sha256:0458fe69728fdce8e1cdaad75e71300f13973fe202c239decb62ac5ce962acfc"
  ],
  "random_seed": 20260744,
  "renderer": "playwright_chromium_svg_rasterizer",
  "renderer_version": "playwright 1.60.0; chromium 148.0.7778.96",
  "sample_id": "sample_000130",
  "schema_version": "provenance_chain_v1",
  "source_asset_hash": "sha256:0458fe69728fdce8e1cdaad75e71300f13973fe202c239decb62ac5ce962acfc",
  "source_path": "svg/sample_000130.svg",
  "source_type": "svg",
  "style_id": "minimal_white",
  "template_family": "svg_flowchart_diagram",
  "wordlist_version": "local_wordlists_v1"
}
